<?xml version="1.0" encoding="UTF-8"?>
<!DOCTYPE plist PUBLIC "-//Apple//DTD PLIST 1.0//EN" "http://www.apple.com/DTDs/PropertyList-1.0.dtd"/>

<plist version="1.0">
    <dict>
        <key>ROOT</key>
        <array>
            <dict>
                <key>id</key>
                <string>3541</string>
                <key>objectA</key>
                <string>3434</string>
                <key>objectB</key>
                <string>3447</string>
            </dict>
            <dict>
                <key>id</key>
                <string>5171</string>
                <key>objectA</key>
                <string>5168</string>
                <key>objectB</key>
                <string>5169</string>
            </dict>
            <dict>
                <key>id</key>
                <string>6849</string>
                <key>objectA</key>
                <string>6839</string>
                <key>objectB</key>
                <string>6847</string>
            </dict>
            <dict>
                <key>id</key>
                <string>6850</string>
                <key>objectA</key>
                <string>6847</string>
                <key>objectB</key>
                <string>6845</string>
            </dict>
            <dict>
                <key>id</key>
                <string>6851</string>
                <key>objectA</key>
                <string>6843</string>
                <key>objectB</key>
                <string>6845</string>
            </dict>
        </array>
    </dict>
</plist>
